confultimate/__init__.py
confultimate/conf_ultimate.py
tests/__init__.py
tests/conf_ultimate/__init__.py
tests/conf_ultimate/test_conf_ultimate.py
confultimate-0.2.6.dist-info/LICENCE
confultimate-0.2.6.dist-info/METADATA
confultimate-0.2.6.dist-info/WHEEL
confultimate-0.2.6.dist-info/top_level.txt
confultimate-0.2.6.dist-info/RECORD
