Metadata-Version: 2.1
Name: confultimate
Version: 0.2.6
Summary: confultimate
Home-page: https://github.com/GuillaumeEscande/confultimate
Author: Escande Guillaume
Author-email: escande.guillaume@gmail.com
License: UNKNOWN
Keywords: conf
Platform: UNKNOWN
Requires-Dist: jsonmerge (==1.7.0)
